MANIFEST.in
setup.py
pcard/__init__.py
pcard/gen.py
pcard/server.py
pcard.egg-info/PKG-INFO
pcard.egg-info/SOURCES.txt
pcard.egg-info/dependency_links.txt
pcard.egg-info/entry_points.txt
pcard.egg-info/not-zip-safe
pcard.egg-info/requires.txt
pcard.egg-info/top_level.txt