Metadata-Version: 1.0
Name: pcard
Version: 0.1
Summary: Generates a Password card
Home-page: UNKNOWN
Author: Tarek Ziade
Author-email: tarek@ziade.org
License: MIT
Platform: UNKNOWN
